EduJornal/__init__.py
EduJornal-1.5.3.dist-info/LICENSE.txt
EduJornal-1.5.3.dist-info/METADATA
EduJornal-1.5.3.dist-info/WHEEL
EduJornal-1.5.3.dist-info/top_level.txt
EduJornal-1.5.3.dist-info/RECORD
