Metadata-Version: 2.1
Name: EduJornal
Version: 1.5.3
Summary: UNKNOWN
Author: RFfront
Author-email: goster5@yandex.ru
License: MIT
Platform: UNKNOWN
License-File: LICENSE.txt
Requires-Dist: numpy (==1.22.2)
Requires-Dist: xlwt (==1.3.0)
Requires-Dist: xlrd (==2.0.1)
